{
	"Version": 3,
	"Meta": {
		"Duration": 1.4,
		"Fps": 30.0,
		"Loop": true,
		"AreBeziersRestricted": true,
		"CurveCount": 2,
		"TotalSegmentCount": 3,
		"TotalPointCount": 9,
		"UserDataCount": 0,
		"TotalUserDataSize": 0
	},
	"Curves": [
		{
			"Target": "Parameter",
			"Id": "ParamBreath",
			"Segments": [
				0,
				0,
				1,
				0.244,
				0,
				0.489,
				1,
				0.733,
				1,
				1,
				0.956,
				1,
				1.178,
				0,
				1.4,
				0
			]
		},
		{
			"Target": "Parameter",
			"Id": "ParamHairFront",
			"Segments": [
				0,
				1,
				0,
				1.4,
				1
			]
		}
	]
}